electrokinetic/__init__.py
electrokinetic/__main__.py
electrokinetic/application.py
electrokinetic/constants.py
electrokinetic/classes/__init__.py
electrokinetic/classes/cells.py
electrokinetic/classes/colloids.py
electrokinetic/classes/electrolytes.py
electrokinetic/classes/particles.py
electrokinetic/classes/transducers.py
electrokinetic/control/__init__.py
electrokinetic/control/siglent.py
electrokinetic/control/transducer_control.py
electrokinetic/gui/QSliderWithText.py
electrokinetic/gui/advanced_args.py
electrokinetic/gui/basic_args.py
electrokinetic/gui/basic_gui.py
electrokinetic/gui/customSlider.py
electrokinetic/gui/labelSlider.py
electrokinetic/gui/labeled_slider.py
electrokinetic/gui/resources.py
electrokinetic/gui/slider_with_value.py
electrokinetic/gui/tkslider.py
electrokinetic/gui/ui_mainwindow.py
electrokinetic/gui/widget_gaussian.py
electrokinetic/ivp/__init__.py
electrokinetic/ivp/burst.py
electrokinetic/ivp/envelope.py
electrokinetic/ivp/furukawa.py
electrokinetic/ivp/ivptools.py
electrokinetic/ivp/k_wave.py
electrokinetic/ivp/peaks.py
electrokinetic/ivp/pydsr_examples.py
electrokinetic/ivp/salve.py
electrokinetic/ivp/signal.py
electrokinetic/ivp/stride.py
electrokinetic/ivp/tom.py
electrokinetic/utils/__init__.py
electrokinetic/utils/file_utils.py
electrokinetic-0.0.3.dist-info/licenses/LICENSE
electrokinetic-0.0.3.dist-info/METADATA
electrokinetic-0.0.3.dist-info/WHEEL
electrokinetic-0.0.3.dist-info/top_level.txt
electrokinetic-0.0.3.dist-info/RECORD
