Metadata-Version: 2.4
Name: electrokinetic
Version: 0.0.3
Summary: CVP/IVP/CVI/IVI analysis software in Python
Author-email: "Paul J.M. van Kan" <pjm@vankanscientific.nl>
Project-URL: Homepage, https://bitbucket.org/deltares/electrokinetic/
Classifier: Programming Language :: Python :: 3
Classifier: License :: OSI Approved :: GNU General Public License v3 or later (GPLv3+)
Classifier: Operating System :: OS Independent
Requires-Python: >=3.11
License-File: LICENSE
Dynamic: license-file
